[
    {
      "name": "Anderson Silva",
      "wins": 34,
      "losses": 11,
      "draws": 0,
      "weightClass": "Meso médio"
    },
    {
      "name": "Jon Jones",
      "wins": 26,
      "losses": 1,
      "draws": 0,
      "weightClass": "Peso meio pesado"
    },
    {
      "name": "Khabib Nurmagomedov",
      "wins": 29,
      "losses": 0,
      "draws": 0,
      "weightClass": "Peso leve"
    },
    {
      "name": "Amanda Nunes",
      "wins": 21,
      "losses": 4,
      "draws": 0,
      "weightClass": "Peso galo"
    }
  ]
  